async_drf_api/conf.py
async_drf_api/setup.py
async_drf_api/orm/__init__.py
async_drf_api/orm/connection.py
async_drf_api/orm/field.py
async_drf_api/orm/models.py
async_drf_api/orm/query.py
async_drf_api/serializers/__init__.py
async_drf_api/serializers/base.py
async_drf_api/views/__init__.py
async_drf_api/views/api_view.py
async_drf_api/views/generic.py
async_drf_api/views/router.py
async_drf_api/web/__init__.py
async_drf_api/web/app.py
async_drf_api/web/middleware.py
async_drf_api/web/request.py
async_drf_api/web/response.py
async_drf_api/web/router.py
async_drf_api-0.3.0.dist-info/METADATA
async_drf_api-0.3.0.dist-info/WHEEL
async_drf_api-0.3.0.dist-info/top_level.txt
async_drf_api-0.3.0.dist-info/RECORD
