Metadata-Version: 2.4
Name: async-drf-api
Version: 0.3.0
Summary: An asynchronous Web API framework based on Starlette, inspired by Django REST Framework
Home-page: https://github.com/sixsfish/async_drf_api
Author: sixsfish
Author-email: sixsfish <sixsfish@foxmail.com>
License: MIT
Project-URL: Homepage, https://github.com/sixsfish/async_drf_api
Project-URL: Repository, https://github.com/sixsfish/async_drf_api
Classifier: Programming Language :: Python :: 3
Classifier: Programming Language :: Python :: 3.12
Classifier: License :: OSI Approved :: MIT License
Classifier: Operating System :: OS Independent
Classifier: Framework :: AsyncIO
Classifier: Topic :: Internet :: WWW/HTTP :: HTTP Servers
Classifier: Topic :: Software Development :: Libraries :: Python Modules
Requires-Python: >=3.12
Requires-Dist: starlette>=0.27.0
Requires-Dist: uvicorn[standard]>=0.23.0
Dynamic: author
Dynamic: home-page
Dynamic: requires-python
